close_dot_io/__about__.py
close_dot_io/__init__.py
close_dot_io/client.py
close_dot_io/dict_util.py
close_dot_io/enums.py
close_dot_io/security.py
close_dot_io/resources/__init__.py
close_dot_io/resources/activity.py
close_dot_io/resources/base.py
close_dot_io/resources/connected_account.py
close_dot_io/resources/contact.py
close_dot_io/resources/event.py
close_dot_io/resources/lead.py
close_dot_io/resources/opportunity.py
close_dot_io/resources/sequence.py
close_dot_io/resources/smart_view.py
close_dot_io/resources/webhook.py
close_dot_io-0.0.916.dist-info/METADATA
close_dot_io-0.0.916.dist-info/WHEEL
close_dot_io-0.0.916.dist-info/licenses/LICENSE.txt
close_dot_io-0.0.916.dist-info/RECORD
