Metadata-Version: 2.3
Name: close-dot-io
Version: 0.0.916
Summary: Easy interface to work with the Close.io API.
Project-URL: Documentation, https://github.com/unknown/close_dot_io#readme
Project-URL: Issues, https://github.com/unknown/close_dot_io/issues
Project-URL: Source, https://github.com/unknown/close_dot_io
Author-email: Copyfactory <dev@copyfactory.io>
License-Expression: MIT
License-File: LICENSE.txt
Classifier: Development Status :: 4 - Beta
Classifier: Programming Language :: Python
Classifier: Programming Language :: Python :: 3.8
Classifier: Programming Language :: Python :: 3.9
Classifier: Programming Language :: Python :: 3.10
Classifier: Programming Language :: Python :: 3.11
Classifier: Programming Language :: Python :: 3.12
Classifier: Programming Language :: Python :: Implementation :: CPython
Classifier: Programming Language :: Python :: Implementation :: PyPy
Requires-Python: >=3.8
Requires-Dist: pycountry
Requires-Dist: pydantic-extra-types
Requires-Dist: pydantic[email]>=2.5.2
Requires-Dist: requests
